MANIFEST.in
README.md
requirements.txt
setup.py
joker/studio/__init__.py
joker/studio/__main__.py
joker/studio/environ.py
joker/studio/utils.py
joker/studio/alpha/__init__.py
joker/studio/alpha/audio.py
joker/studio/aux/__init__.py
joker/studio/aux/info.py
joker/studio/aux/utils.py
joker/studio/ffmpeg/__init__.py
joker/studio/ffmpeg/conv.py
joker/studio/ffmpeg/crop.py
joker/studio/ffmpeg/fade.py
joker/studio/ffmpeg/filters.py
joker/studio/ffmpeg/split.py
joker/studio/ffmpeg/subtitle.py
joker/studio/ffmpeg/thumb.py
joker/studio/images/__init__.py
joker/studio/images/rotate.py
joker/studio/misc/__init__.py
joker/studio/misc/avatar.py
joker/studio/misc/margin.py
joker/studio/misc/player.py
joker/studio/misc/rename.py
joker/studio/misc/vident.py
joker_studio.egg-info/PKG-INFO
joker_studio.egg-info/SOURCES.txt
joker_studio.egg-info/dependency_links.txt
joker_studio.egg-info/entry_points.txt
joker_studio.egg-info/namespace_packages.txt
joker_studio.egg-info/not-zip-safe
joker_studio.egg-info/requires.txt
joker_studio.egg-info/top_level.txt
tests/test_imports.py