Metadata-Version: 2.1
Name: joker-studio
Version: 0.2.1
Summary: CLI tools for media file editing, wrapping FFmpeg and others
Home-page: https://github.com/frozflame/joker-studio
Author: anonym
Author-email: anonym@example.com
License: GNU General Public License (GPL)
Classifier: Programming Language :: Python
Classifier: Programming Language :: Python :: 3
Classifier: Programming Language :: Python :: 3.9
Classifier: Programming Language :: Python :: 3.10
Classifier: Programming Language :: Python :: 3.11
Classifier: Programming Language :: Python :: 3.12
Classifier: Programming Language :: Python :: 3.13
Classifier: Programming Language :: Python :: 3.14
Requires-Dist: imagehash~=4.3.1
Requires-Dist: joker-cast~=0.5.2
Requires-Dist: joker-stream~=0.5.0
Requires-Dist: joker-textmanip
Requires-Dist: joker~=0.3.3
Requires-Dist: numpy~=2.2.1
Requires-Dist: pillow~=11.0.0
Requires-Dist: pymediainfo~=1.0
Requires-Dist: scipy~=1.14.1
Requires-Dist: volkanic~=0.5.3
